LIVR/__init__.py
LIVR/BuildAliasedRule.py
LIVR/internal_reactor.py
LIVR/Validator.py
LIVR/DEFAULT_RULES.py
LIVR/test/case_handler.py
LIVR/test/test_suite.py
LIVR/test/__init__.py
LIVR/test/livr_test.py
LIVR/test/test_suite/__init__.py
LIVR/test/test_suite/aliases_negative/__init__.py
LIVR/test/test_suite/aliases_negative/01-adult_age/__init__.py
LIVR/Rules/constants.py
LIVR/Rules/String.py
LIVR/Rules/Modifiers.py
LIVR/Rules/Common.py
LIVR/Rules/Numeric.py
LIVR/Rules/__init__.py
LIVR/Rules/Helper.py
LIVR/Rules/Filters.py
LIVR/Rules/Special.py
LIVR/Rules/Meta.py
LIVR-2.0.1.dist-info/RECORD
LIVR-2.0.1.dist-info/top_level.txt
LIVR-2.0.1.dist-info/WHEEL
LIVR-2.0.1.dist-info/metadata.json
LIVR-2.0.1.dist-info/DESCRIPTION.rst
LIVR-2.0.1.dist-info/METADATA
