Metadata-Version: 2.0
Name: LIVR
Version: 2.0.1
Summary: LIVR validator.
Home-page: https://github.com/asholok/python-validator-livr
Author: Ihor Kolosha, Viktor Turstkiy
Author-email: UNKNOWN
License: look into README
Platform: UNKNOWN
